pyannote.video-1.6.3-py3.6-nspkg.pth
pyannote/video/__init__.py
pyannote/video/_version.py
pyannote/video/tracking.py
pyannote/video/video.py
pyannote/video/face/__init__.py
pyannote/video/face/clustering.py
pyannote/video/face/face.py
pyannote/video/face/io.py
pyannote/video/face/openface.py
pyannote/video/face/openface_server.lua
pyannote/video/face/tracking.py
pyannote/video/structure/__init__.py
pyannote/video/structure/shot.py
pyannote/video/structure/thread.py
pyannote/video/utils/__init__.py
pyannote/video/utils/lru_cache.py
pyannote.video-1.6.3.data/scripts/pyannote-face.py
pyannote.video-1.6.3.data/scripts/pyannote-structure.py
pyannote.video-1.6.3.dist-info/LICENSE
pyannote.video-1.6.3.dist-info/METADATA
pyannote.video-1.6.3.dist-info/WHEEL
pyannote.video-1.6.3.dist-info/namespace_packages.txt
pyannote.video-1.6.3.dist-info/pbr.json
pyannote.video-1.6.3.dist-info/top_level.txt
pyannote.video-1.6.3.dist-info/RECORD
